fastpluggy_plugin/postgres_tools/__init__.py
fastpluggy_plugin/postgres_tools/plugin.py
fastpluggy_plugin/postgres_tools/routers/__init__.py
fastpluggy_plugin/postgres_tools/routers/alerts.py
fastpluggy_plugin/postgres_tools/routers/connections.py
fastpluggy_plugin/postgres_tools/routers/dashboard.py
fastpluggy_plugin/postgres_tools/routers/db_size.py
fastpluggy_plugin/postgres_tools/routers/extensions.py
fastpluggy_plugin/postgres_tools/routers/indexes.py
fastpluggy_plugin/postgres_tools/routers/queries.py
fastpluggy_plugin/postgres_tools/routers/replication.py
fastpluggy_plugin/postgres_tools/routers/sequences.py
fastpluggy_plugin/postgres_tools/routers/tables.py
fastpluggy_plugin/postgres_tools/routers/vacuum.py
fastpluggy_plugin/postgres_tools/templates/dashboard_cards.html.j2
fastpluggy_plugin/postgres_tools/utils/__init__.py
fastpluggy_plugin/postgres_tools/utils/db_utils.py
fastpluggy_postgres_tools-0.1.34.dist-info/METADATA
fastpluggy_postgres_tools-0.1.34.dist-info/WHEEL
fastpluggy_postgres_tools-0.1.34.dist-info/entry_points.txt
fastpluggy_postgres_tools-0.1.34.dist-info/top_level.txt
fastpluggy_postgres_tools-0.1.34.dist-info/RECORD
