Metadata-Version: 2.4
Name: fastpluggy-postgres-tools
Version: 0.1.34
Summary: PostgreSQL database monitoring and management plugin for FastPluggy
License-Expression: MIT
Requires-Python: >=3.10
Requires-Dist: sqlalchemy>=2.0.0
Requires-Dist: fastpluggy-ui-tools>=0.0.4
